eFELunit/__init__.py
eFELunit/utils.py
eFELunit/capabilities/__init__.py
eFELunit/capabilities/cap_SomaReceivesCurrentProducesMembranePotential.py
eFELunit/plots/__init__.py
eFELunit/scores/__init__.py
eFELunit/scores/score_RMS.py
eFELunit/tests/__init__.py
eFELunit/tests/test_Ferg2014_APFrequency.py
eFELunit/tests/test_eFELfeatureTest.py
eFELunit-2.0.3.dist-info/LICENSE.txt
eFELunit-2.0.3.dist-info/METADATA
eFELunit-2.0.3.dist-info/WHEEL
eFELunit-2.0.3.dist-info/dependency_links.txt
eFELunit-2.0.3.dist-info/top_level.txt
eFELunit-2.0.3.dist-info/RECORD
