Metadata-Version: 2.1
Name: eFELunit
Version: 2.0.3
Summary: A SciUnit library for data-driven testing of neuronal morphologies.
Home-page: https://github.com/appukuttan-shailesh/eFELunit
Author: Shailesh Appukuttan, Andrew Davison
Author-email: shailesh.appukuttan@unic.cnrs-gif.fr, andrew.davison@unic.cnrs-gif.fr
License: MIT
Keywords: eFEL,electrophysiology,electrical,testing,validation framework
Platform: UNKNOWN
Requires-Dist: neo
Requires-Dist: sciunit (>=0.1.5.2)
